{
  "subtitle": "", 
  "description": "DES VOIX DE FILLES\r\n", 
  "language": "fre_FR", 
  "title": " LA GIRL DECLARATION", 
  "primary_category": "bacd97a95386494abc571c419392c7d4", 
  "created_at": "2016-05-15T15:12:51.269127+00:00", 
  "featured_in_category": false, 
  "modified_at": "2016-05-15T15:12:51.269350+00:00", 
  "_version": {
    "package_version": "1.4.4", 
    "language_version": "2.7.6", 
    "language": "python", 
    "language_version_string": "2.7.6 (default, Jun 22 2015, 18:01:27) \n[GCC 4.8.2]", 
    "package": "elastic-git"
  }, 
  "linked_pages": [], 
  "id": null, 
  "content": "Je ne suis pas venue au monde pour \u00eatre invisible. \r\n \r\nJe ne suis pas n\u00e9e pour \u00eatre d\u00e9ni\u00e9e. \r\n \r\nJe ne suis pas n\u00e9e juste pour appartenir \u00e0 quelqu'un d'autre. \r\n \r\nJe m'appartiens. \r\n \r\nJ'ai une voix et je vais l'utiliser. \r\n \r\nJ'ai des r\u00eaves inoubliables. \r\n \r\nJ'ai un nom et il n'est pas\r\nAnonyme\r\nou Insignifiant\r\nou Indigne\r\nOu attendre davantage pour \u00eatre appel\u00e9. \r\n \r\nUnjour, ils diront que c'\u00e9tait le moment o\u00f9 le monde se rend compte de mon potentiel. \r\n \r\nC'est le moment o\u00f9 l'on me permet de surprendre. \r\n \r\nC'est le moment o\u00f9 mon \u00e9volution ne vous fait plus peur. \r\n \r\nC'est le moment o\u00f9 \u00eatre une fille devient\r\nMa force\r\nMon refuge\r\nNon pas ma peine. \r\n \r\nC'est le moment o\u00f9 le monde voit\r\nque je suis retenue par chaque probl\u00e8me et   \r\nje suis la cl\u00e9 \u00e0 toutes les solutions. \r\n \r\nC'est le moment o\u00f9 une fille plus une fille plus une fille et 250 millions d'autres filles\r\nDisent \u00e0 hautes voix\r\nC'est notre moment. \r\n \r\nC'est mon moment.\r\n \r\nCeci,\r\nOui ceci\r\nest le moment\r\n", 
  "source": null, 
  "featured": false, 
  "author_tags": [], 
  "image": null, 
  "published": null, 
  "position": 0, 
  "image_host": "http://thumbor.unicore.io", 
  "slug": "girl-declaration", 
  "uuid": "2bfea033fd5541aaaffc3d1a0a50cda5"
}