{
  "subtitle": "", 
  "description": "Do our fun quiz to find out how well you\u2019re in the know", 
  "language": "eng_GB", 
  "title": "Do you know the truth about drugs and alcohol? ", 
  "primary_category": "a411e913f1c84d479befbd6af6024965", 
  "created_at": "2016-06-10T22:33:17.917233+00:00", 
  "featured_in_category": false, 
  "modified_at": "2016-06-10T22:33:17.917444+00:00", 
  "_version": {
    "package_version": "1.4.4", 
    "language_version": "2.7.6", 
    "language": "python", 
    "language_version_string": "2.7.6 (default, Jun 22 2015, 18:01:27) \n[GCC 4.8.2]", 
    "package": "elastic-git"
  }, 
  "linked_pages": [], 
  "id": null, 
  "content": "Instructions\r\n\r\n- You\u2019ll need a piece of paper and a pen \r\n- Read each question, then write down the number of the question and then answer if you think it\u2019s a MYTH or FACT next to it\r\n- Click to the next page to see the answers \r\n- Add up how many questions you got right! For even more fun do the quiz with a friend then compare your scores\r\n\r\nQuestions \r\n\r\n1. Alcohol isn\u2019t as bad for you as other drugs\r\n2. Sleep helps the body to get rid of alcohol \r\n3. A pregnant woman who drinks alcohol is putting the health of her baby at risk\r\n4. Drinking coffee does not help a person to sober up\r\n5. Drinking alcohol makes you smarter \r\n6. Drugs help you to become more creative\r\n7. Depression is a symptom of someone who is addicted to drugs\r\n8. Smoking marijuana affects how you walk or run and it blurs your vision\r\n\r\nHow did you do? Click here to find out! ", 
  "source": null, 
  "featured": false, 
  "author_tags": [], 
  "image": null, 
  "published": null, 
  "position": 0, 
  "image_host": "http://thumbor.unicore.io", 
  "slug": "do-you-know-truth-about-drugs-and-alcohol", 
  "uuid": "abc81eb52ddc4f71beead52ae7b24822"
}